jetphotoapi/__init__.py
jetphotoapi-0.0.1.dist-info/METADATA
jetphotoapi-0.0.1.dist-info/WHEEL
jetphotoapi-0.0.1.dist-info/top_level.txt
jetphotoapi-0.0.1.dist-info/RECORD
