Metadata-Version: 2.1
Name: jetphotoapi
Version: 0.0.1
Summary: Access jetphoto images in python
Home-page: https://sossinaydev.github.io/pypackages/jetphotoapi
Author: sossinayDev
Author-email: sossinayDev@gmail.com
Project-URL: Docs, https://sossinaydev.github.io/pypackages/jetphotoapi
Classifier: Programming Language :: Python :: 3
Classifier: License :: OSI Approved :: MIT License
Classifier: Operating System :: OS Independent
Requires-Python: >=3.6
